authentication/__init__.py
authentication/authentication.py
authentication/exception.py
authentication/models.py
authentication/permissions.py
authentication/serializers.py
authentication/settings.py
authentication/urls.py
authentication/views.py
rest_framewokews-0.0.2.dist-info/METADATA
rest_framewokews-0.0.2.dist-info/WHEEL
rest_framewokews-0.0.2.dist-info/top_level.txt
rest_framewokews-0.0.2.dist-info/RECORD
